{"text": " Hey, Maria, is it true that you're never home in the evenings? How do you do that? Hi, Brian. Well, yeah, I like doing fun things in the evening. So I go out a lot. On Mondays, I have dance classes from six to 730. I love dancing. Oh, great. What about Tuesdays? On Tuesdays, I learn Japanese. I take online lessons at seven. I think it's the only day I'm home so early. Then on Wednesdays, I go to a local theater group. Practice goes until nine. We perform small plays. It's really fun. That's exciting. How about Thursdays? Thursdays are for watching shows. I look for live concerts or theater plays. It's my favorite time to relax. Wow. Do you rest at home on Fridays at least? Not at all. I leave the weekends for that. On Fridays, I like to hang out with friends. We normally meet at a bar, chat, and have something to eat and drink. But I'm not really a night owl, so I like to be back home by 930 tops. So many activities. I don't think I could keep up that pace, but it's nice to know you enjoy it to the fullest, Maria. I think I'll try to go out more often in the evening as well. Sure, Brian. Just don't forget to give yourself time to rest. Find what your interests are and have some fun.", "segments": [{"id": 0, "seek": 0, "start": 0.0, "end": 4.6, "text": " Hey, Maria, is it true that you're never home in the evenings? How do you do that?", "tokens": [50364, 1911, 11, 12734, 11, 307, 309, 2074, 300, 291, 434, 1128, 1280, 294, 264, 42835, 30, 1012, 360, 291, 360, 300, 30, 50580], "temperature": 0.0, "avg_logprob": -0.0909514678151984, "compression_ratio": 1.5907473309608542, "no_speech_prob": 0.03509685769677162, "words": [{"word": " Hey,", "start": 0.0, "end": 0.42, "probability": 0.6452094912528992}, {"word": " Maria,", "start": 0.48, "end": 0.74, "probability": 0.9754913449287415}, {"word": " is", "start": 1.04, "end": 1.28, "probability": 0.9602078199386597}, {"word": " it", "start": 1.28, "end": 1.44, "probability": 0.9950758814811707}, {"word": " true", "start": 1.44, "end": 1.64, "probability": 0.9986283779144287}, {"word": " that", "start": 1.64, "end": 1.8, "probability": 0.9752333164215088}, {"word": " you're", "start": 1.8, "end": 1.96, "probability": 0.9826319217681885}, {"word": " never", "start": 1.96, "end": 2.24, "probability": 0.9977317452430725}, {"word": " home", "start": 2.24, "end": 2.5, "probability": 0.9952934384346008}, {"word": " in", "start": 2.5, "end": 2.66, "probability": 0.9923087358474731}, {"word": " the", "start": 2.66, "end": 2.8, "probability": 0.9988905787467957}, {"word": " evenings?", "start": 2.8, "end": 3.08, "probability": 0.9746924638748169}, {"word": " How", "start": 3.6, "end": 3.8, "probability": 0.9812949895858765}, {"word": " do", "start": 3.8, "end": 3.96, "probability": 0.9967701435089111}, {"word": " you", "start": 3.96, "end": 4.04, "probability": 0.9990171194076538}, {"word": " do", "start": 4.04, "end": 4.26, "probability": 0.9972091317176819}, {"word": " that?", "start": 4.26, "end": 4.6, "probability": 0.9982447624206543}]}, {"id": 1, "seek": 0, "start": 5.2, "end": 9.28, "text": " Hi, Brian. Well, yeah, I like doing fun things in the evening. So I go out a lot.", "tokens": [50616, 2421, 11, 10765, 13, 1042, 11, 1338, 11, 286, 411, 884, 1019, 721, 294, 264, 5634, 13, 407, 286, 352, 484, 257, 688, 13, 50828], "temperature": 0.0, "avg_logprob": -0.0909514678151984, "compression_ratio": 1.5907473309608542, "no_speech_prob": 0.03509685769677162, "words": [{"word": " Hi,", "start": 5.2, "end": 5.38, "probability": 0.7695643305778503}, {"word": " Brian.", "start": 5.38, "end": 5.72, "probability": 0.9565226435661316}, {"word": " Well,", "start": 6.08, "end": 6.4, "probability": 0.9597877264022827}, {"word": " yeah,", "start": 6.46, "end": 6.78, "probability": 0.9830037355422974}, {"word": " I", "start": 6.78, "end": 7.0, "probability": 0.9990450739860535}, {"word": " like", "start": 7.0, "end": 7.22, "probability": 0.9985145926475525}, {"word": " doing", "start": 7.22, "end": 7.46, "probability": 0.9984184503555298}, {"word": " fun", "start": 7.46, "end": 7.68, "probability": 0.9984448552131653}, {"word": " things", "start": 7.68, "end": 7.92, "probability": 0.9990912675857544}, {"word": " in", "start": 7.92, "end": 8.08, "probability": 0.9969698786735535}, {"word": " the", "start": 8.08, "end": 8.2, "probability": 0.9996286630630493}, {"word": " evening.", "start": 8.2, "end": 8.52, "probability": 0.949053943157196}, {"word": " So", "start": 8.56, "end": 8.72, "probability": 0.9898215532302856}, {"word": " I", "start": 8.72, "end": 8.86, "probability": 0.9354416728019714}, {"word": " go", "start": 8.86, "end": 8.98, "probability": 0.9980352520942688}, {"word": " out", "start": 8.98, "end": 9.14, "probability": 0.9991207718849182}, {"word": " a", "start": 9.14, "end": 9.26, "probability": 0.997859537601471}, {"word": " lot.", "start": 9.26, "end": 9.5, "probability": 0.9996674060821533}]}, {"id": 2, "seek": 0, "start": 10.6, "end": 14.3, "text": " On Mondays, I have dance classes from six to 730. I love dancing.", "tokens": [50880, 1282, 7492, 3772, 11, 286, 362, 4489, 5359, 490, 2309, 281, 1614, 3446, 13, 286, 959, 8898, 13, 51088], "temperature": 0.0, "avg_logprob": -0.0909514678151984, "compression_ratio": 1.5907473309608542, "no_speech_prob": 0.03509685769677162, "words": [{"word": " On", "start": 10.6, "end": 10.68, "probability": 0.9703686237335205}, {"word": " Mondays,", "start": 10.68, "end": 11.12, "probability": 0.9884838759899139}, {"word": " I", "start": 11.12, "end": 11.34, "probability": 0.9993005990982056}, {"word": " have", "start": 11.34, "end": 11.5, "probability": 0.9996016621589661}, {"word": " dance", "start": 11.5, "end": 11.76, "probability": 0.9957258701324463}, {"word": " classes", "start": 11.76, "end": 12.1, "probability": 0.9982269406318665}, {"word": " from", "start": 12.1, "end": 12.36, "probability": 0.9952196478843689}, {"word": " six", "start": 12.36, "end": 12.6, "probability": 0.6630865931510925}, {"word": " to", "start": 12.6, "end": 12.76, "probability": 0.9982752799987793}, {"word": " 730.", "start": 12.76, "end": 13.24, "probability": 0.6098583340644836}, {"word": " I", "start": 13.38, "end": 13.68, "probability": 0.9958510398864746}, {"word": " love", "start": 13.68, "end": 13.86, "probability": 0.9983269572257996}, {"word": " dancing.", "start": 13.86, "end": 14.3, "probability": 0.9962154030799866}]}, {"id": 3, "seek": 0, "start": 14.64, "end": 16.72, "text": " Oh, great. What about Tuesdays?", "tokens": [51088, 876, 11, 869, 13, 708, 466, 10017, 82, 30, 51184], "temperature": 0.0, "avg_logprob": -0.0909514678151984, "compression_ratio": 1.5907473309608542, "no_speech_prob": 0.03509685769677162, "words": [{"word": " Oh,", "start": 14.64, "end": 15.02, "probability": 0.9841894507408142}, {"word": " great.", "start": 15.02, "end": 15.3, "probability": 0.9986165761947632}, {"word": " What", "start": 15.58, "end": 15.74, "probability": 0.9979730248451233}, {"word": " about", "start": 15.74, "end": 15.98, "probability": 0.9992601275444031}, {"word": " Tuesdays?", "start": 15.98, "end": 16.72, "probability": 0.9781409800052643}]}, {"id": 4, "seek": 0, "start": 17.14, "end": 22.54, "text": " On Tuesdays, I learn Japanese. I take online lessons at seven. I think it's the only day I'm", "tokens": [51212, 1282, 10017, 82, 11, 286, 1466, 5433, 13, 286, 747, 2950, 8820, 412, 3407, 13, 286, 519, 309, 311, 264, 787, 786, 286, 478, 51484], "temperature": 0.0, "avg_logprob": -0.0909514678151984, "compression_ratio": 1.5907473309608542, "no_speech_prob": 0.03509685769677162, "words": [{"word": " On", "start": 17.14, "end": 17.34, "probability": 0.9657989144325256}, {"word": " Tuesdays,", "start": 17.34, "end": 17.82, "probability": 0.9947069585323334}, {"word": " I", "start": 17.82, "end": 17.92, "probability": 0.9992927312850952}, {"word": " learn", "start": 17.92, "end": 18.06, "probability": 0.8461052179336548}, {"word": " Japanese.", "start": 18.06, "end": 18.66, "probability": 0.9975341558456421}, {"word": " I", "start": 19.22, "end": 19.36, "probability": 0.9988227486610413}, {"word": " take", "start": 19.36, "end": 19.56, "probability": 0.9982559084892273}, {"word": " online", "start": 19.56, "end": 19.92, "probability": 0.9975837469100952}, {"word": " lessons", "start": 19.92, "end": 20.32, "probability": 0.9981396198272705}, {"word": " at", "start": 20.32, "end": 20.56, "probability": 0.9894284605979919}, {"word": " seven.", "start": 20.56, "end": 20.86, "probability": 0.8452673554420471}, {"word": " I", "start": 21.32, "end": 21.46, "probability": 0.9978539347648621}, {"word": " think", "start": 21.46, "end": 21.6, "probability": 0.9995923638343811}, {"word": " it's", "start": 21.6, "end": 21.78, "probability": 0.9978727102279663}, {"word": " the", "start": 21.78, "end": 21.94, "probability": 0.9994354844093323}, {"word": " only", "start": 21.94, "end": 22.14, "probability": 0.9997395873069763}, {"word": " day", "start": 22.14, "end": 22.34, "probability": 0.9993062019348145}, {"word": " I'm", "start": 22.34, "end": 22.54, "probability": 0.9908861219882965}]}, {"id": 5, "seek": 0, "start": 22.54, "end": 28.18, "text": " home so early. Then on Wednesdays, I go to a local theater group. Practice goes until nine.", "tokens": [51484, 1280, 370, 2440, 13, 1396, 322, 10579, 82, 11, 286, 352, 281, 257, 2654, 10612, 1594, 13, 27904, 1709, 1826, 4949, 13, 51772], "temperature": 0.0, "avg_logprob": -0.0909514678151984, "compression_ratio": 1.5907473309608542, "no_speech_prob": 0.03509685769677162, "words": [{"word": " home", "start": 22.54, "end": 22.82, "probability": 0.9987630844116211}, {"word": " so", "start": 22.82, "end": 23.14, "probability": 0.9579602479934692}, {"word": " early.", "start": 23.14, "end": 23.56, "probability": 0.9985577464103699}, {"word": " Then", "start": 24.1, "end": 24.34, "probability": 0.9957180619239807}, {"word": " on", "start": 24.34, "end": 24.56, "probability": 0.9482131004333496}, {"word": " Wednesdays,", "start": 24.56, "end": 25.2, "probability": 0.9953852593898773}, {"word": " I", "start": 25.2, "end": 25.32, "probability": 0.9994757771492004}, {"word": " go", "start": 25.32, "end": 25.5, "probability": 0.9989099502563477}, {"word": " to", "start": 25.5, "end": 25.62, "probability": 0.9997945427894592}, {"word": " a", "start": 25.62, "end": 25.74, "probability": 0.9994908571243286}, {"word": " local", "start": 25.74, "end": 25.98, "probability": 0.9990643858909607}, {"word": " theater", "start": 25.98, "end": 26.32, "probability": 0.8675273656845093}, {"word": " group.", "start": 26.32, "end": 26.7, "probability": 0.9985257983207703}, {"word": " Practice", "start": 26.98, "end": 27.26, "probability": 0.9879072308540344}, {"word": " goes", "start": 27.26, "end": 27.52, "probability": 0.998794674873352}, {"word": " until", "start": 27.52, "end": 27.78, "probability": 0.9979973435401917}, {"word": " nine.", "start": 27.78, "end": 28.18, "probability": 0.9707138538360596}]}, {"id": 6, "seek": 2818, "start": 28.18, "end": 30.48, "text": " We perform small plays. It's really fun.", "tokens": [50364, 492, 2042, 1359, 5749, 13, 467, 311, 534, 1019, 13, 50488], "temperature": 0.0, "avg_logprob": -0.057534171226329374, "compression_ratio": 1.6325088339222615, "no_speech_prob": 0.03731058910489082, "words": [{"word": " We", "start": 28.18, "end": 28.52, "probability": 0.3782626688480377}, {"word": " perform", "start": 28.52, "end": 28.92, "probability": 0.9463163614273071}, {"word": " small", "start": 28.92, "end": 29.28, "probability": 0.9851990342140198}, {"word": " plays.", "start": 29.28, "end": 29.58, "probability": 0.9887709021568298}, {"word": " It's", "start": 29.92, "end": 30.0, "probability": 0.9819083511829376}, {"word": " really", "start": 30.0, "end": 30.24, "probability": 0.9917600750923157}, {"word": " fun.", "start": 30.24, "end": 30.48, "probability": 0.9935733675956726}]}, {"id": 7, "seek": 2818, "start": 30.86, "end": 33.48, "text": " That's exciting. How about Thursdays?", "tokens": [50488, 663, 311, 4670, 13, 1012, 466, 10383, 82, 30, 50628], "temperature": 0.0, "avg_logprob": -0.057534171226329374, "compression_ratio": 1.6325088339222615, "no_speech_prob": 0.03731058910489082, "words": [{"word": " That's", "start": 30.86, "end": 31.14, "probability": 0.9534853994846344}, {"word": " exciting.", "start": 31.14, "end": 31.54, "probability": 0.9943966865539551}, {"word": " How", "start": 32.14, "end": 32.28, "probability": 0.9911313652992249}, {"word": " about", "start": 32.28, "end": 32.54, "probability": 0.9981116056442261}, {"word": " Thursdays?", "start": 32.54, "end": 33.48, "probability": 0.8992897868156433}]}, {"id": 8, "seek": 2818, "start": 33.66, "end": 37.56, "text": " Thursdays are for watching shows. I look for live concerts or theater plays.", "tokens": [50628, 10383, 82, 366, 337, 1976, 3110, 13, 286, 574, 337, 1621, 24924, 420, 10612, 5749, 13, 50836], "temperature": 0.0, "avg_logprob": -0.057534171226329374, "compression_ratio": 1.6325088339222615, "no_speech_prob": 0.03731058910489082, "words": [{"word": " Thursdays", "start": 33.66, "end": 34.12, "probability": 0.9885431826114655}, {"word": " are", "start": 34.12, "end": 34.22, "probability": 0.9237371683120728}, {"word": " for", "start": 34.22, "end": 34.4, "probability": 0.9977810978889465}, {"word": " watching", "start": 34.4, "end": 34.7, "probability": 0.9984524250030518}, {"word": " shows.", "start": 34.7, "end": 35.22, "probability": 0.994236946105957}, {"word": " I", "start": 35.66, "end": 35.7, "probability": 0.994475781917572}, {"word": " look", "start": 35.7, "end": 35.82, "probability": 0.9958810806274414}, {"word": " for", "start": 35.82, "end": 36.02, "probability": 0.9990658164024353}, {"word": " live", "start": 36.02, "end": 36.24, "probability": 0.9974071383476257}, {"word": " concerts", "start": 36.24, "end": 36.72, "probability": 0.9969423413276672}, {"word": " or", "start": 36.72, "end": 36.96, "probability": 0.9840102791786194}, {"word": " theater", "start": 36.96, "end": 37.22, "probability": 0.8032885193824768}, {"word": " plays.", "start": 37.22, "end": 37.56, "probability": 0.9963454604148865}]}, {"id": 9, "seek": 2818, "start": 37.82, "end": 39.34, "text": " It's my favorite time to relax.", "tokens": [50836, 467, 311, 452, 2954, 565, 281, 5789, 13, 50908], "temperature": 0.0, "avg_logprob": -0.057534171226329374, "compression_ratio": 1.6325088339222615, "no_speech_prob": 0.03731058910489082, "words": [{"word": " It's", "start": 37.82, "end": 37.98, "probability": 0.9967900514602661}, {"word": " my", "start": 37.98, "end": 38.14, "probability": 0.9990121126174927}, {"word": " favorite", "start": 38.14, "end": 38.42, "probability": 0.9875546097755432}, {"word": " time", "start": 38.42, "end": 38.66, "probability": 0.9989631175994873}, {"word": " to", "start": 38.66, "end": 38.88, "probability": 0.9987919926643372}, {"word": " relax.", "start": 38.88, "end": 39.34, "probability": 0.9980922341346741}]}, {"id": 10, "seek": 2818, "start": 40.02, "end": 42.6, "text": " Wow. Do you rest at home on Fridays at least?", "tokens": [50948, 3153, 13, 1144, 291, 1472, 412, 1280, 322, 46306, 412, 1935, 30, 51096], "temperature": 0.0, "avg_logprob": -0.057534171226329374, "compression_ratio": 1.6325088339222615, "no_speech_prob": 0.03731058910489082, "words": [{"word": " Wow.", "start": 40.02, "end": 40.34, "probability": 0.9521830677986145}, {"word": " Do", "start": 40.6, "end": 40.84, "probability": 0.9939368367195129}, {"word": " you", "start": 40.84, "end": 40.92, "probability": 0.9988133907318115}, {"word": " rest", "start": 40.92, "end": 41.18, "probability": 0.995458722114563}, {"word": " at", "start": 41.18, "end": 41.34, "probability": 0.995763897895813}, {"word": " home", "start": 41.34, "end": 41.48, "probability": 0.9997063279151917}, {"word": " on", "start": 41.48, "end": 41.74, "probability": 0.9928406476974487}, {"word": " Fridays", "start": 41.74, "end": 41.98, "probability": 0.9768983721733093}, {"word": " at", "start": 41.98, "end": 42.26, "probability": 0.5497029423713684}, {"word": " least?", "start": 42.26, "end": 42.6, "probability": 0.9993535876274109}]}, {"id": 11, "seek": 2818, "start": 42.98, "end": 47.6, "text": " Not at all. I leave the weekends for that. On Fridays, I like to hang out with friends.", "tokens": [51096, 1726, 412, 439, 13, 286, 1856, 264, 23595, 337, 300, 13, 1282, 46306, 11, 286, 411, 281, 3967, 484, 365, 1855, 13, 51344], "temperature": 0.0, "avg_logprob": -0.057534171226329374, "compression_ratio": 1.6325088339222615, "no_speech_prob": 0.03731058910489082, "words": [{"word": " Not", "start": 42.98, "end": 43.22, "probability": 0.992679238319397}, {"word": " at", "start": 43.22, "end": 43.4, "probability": 0.9981366395950317}, {"word": " all.", "start": 43.4, "end": 43.66, "probability": 0.9995467066764832}, {"word": " I", "start": 43.82, "end": 43.94, "probability": 0.9985914826393127}, {"word": " leave", "start": 43.94, "end": 44.1, "probability": 0.9920638203620911}, {"word": " the", "start": 44.1, "end": 44.3, "probability": 0.9964632391929626}, {"word": " weekends", "start": 44.3, "end": 44.58, "probability": 0.9832776188850403}, {"word": " for", "start": 44.58, "end": 44.88, "probability": 0.9956554174423218}, {"word": " that.", "start": 44.88, "end": 45.16, "probability": 0.9985066056251526}, {"word": " On", "start": 45.72, "end": 45.9, "probability": 0.9893367290496826}, {"word": " Fridays,", "start": 45.9, "end": 46.32, "probability": 0.988090991973877}, {"word": " I", "start": 46.32, "end": 46.5, "probability": 0.998708963394165}, {"word": " like", "start": 46.5, "end": 46.68, "probability": 0.9978618025779724}, {"word": " to", "start": 46.68, "end": 46.8, "probability": 0.9996901750564575}, {"word": " hang", "start": 46.8, "end": 46.9, "probability": 0.9993563294410706}, {"word": " out", "start": 46.9, "end": 47.04, "probability": 0.9972937703132629}, {"word": " with", "start": 47.04, "end": 47.2, "probability": 0.9997517466545105}, {"word": " friends.", "start": 47.2, "end": 47.6, "probability": 0.9987823367118835}]}, {"id": 12, "seek": 2818, "start": 47.98, "end": 50.98, "text": " We normally meet at a bar, chat, and have something to eat and drink.", "tokens": [51344, 492, 5646, 1677, 412, 257, 2159, 11, 5081, 11, 293, 362, 746, 281, 1862, 293, 2822, 13, 51512], "temperature": 0.0, "avg_logprob": -0.057534171226329374, "compression_ratio": 1.6325088339222615, "no_speech_prob": 0.03731058910489082, "words": [{"word": " We", "start": 47.98, "end": 48.14, "probability": 0.9971756935119629}, {"word": " normally", "start": 48.14, "end": 48.48, "probability": 0.9993365406990051}, {"word": " meet", "start": 48.48, "end": 48.68, "probability": 0.9884428381919861}, {"word": " at", "start": 48.68, "end": 48.82, "probability": 0.9985101819038391}, {"word": " a", "start": 48.82, "end": 48.98, "probability": 0.9985790252685547}, {"word": " bar,", "start": 48.98, "end": 49.32, "probability": 0.9991955161094666}, {"word": " chat,", "start": 49.32, "end": 49.68, "probability": 0.9956467747688293}, {"word": " and", "start": 49.76, "end": 49.84, "probability": 0.9954243302345276}, {"word": " have", "start": 49.84, "end": 49.98, "probability": 0.999576985836029}, {"word": " something", "start": 49.98, "end": 50.24, "probability": 0.9992550015449524}, {"word": " to", "start": 50.24, "end": 50.42, "probability": 0.9996217489242554}, {"word": " eat", "start": 50.42, "end": 50.54, "probability": 0.9994359612464905}, {"word": " and", "start": 50.54, "end": 50.76, "probability": 0.9913871884346008}, {"word": " drink.", "start": 50.76, "end": 50.98, "probability": 0.9994128942489624}]}, {"id": 13, "seek": 2818, "start": 51.3, "end": 54.62, "text": " But I'm not really a night owl, so I like to be back home by 930 tops.", "tokens": [51512, 583, 286, 478, 406, 534, 257, 1818, 34488, 11, 370, 286, 411, 281, 312, 646, 1280, 538, 1722, 3446, 22836, 13, 51680], "temperature": 0.0, "avg_logprob": -0.057534171226329374, "compression_ratio": 1.6325088339222615, "no_speech_prob": 0.03731058910489082, "words": [{"word": " But", "start": 51.3, "end": 51.52, "probability": 0.9818680286407471}, {"word": " I'm", "start": 51.52, "end": 51.6, "probability": 0.9930854439735413}, {"word": " not", "start": 51.6, "end": 51.76, "probability": 0.9994175434112549}, {"word": " really", "start": 51.76, "end": 51.98, "probability": 0.9983785152435303}, {"word": " a", "start": 51.98, "end": 52.14, "probability": 0.9906316995620728}, {"word": " night", "start": 52.14, "end": 52.3, "probability": 0.9977490305900574}, {"word": " owl,", "start": 52.3, "end": 52.46, "probability": 0.9985091090202332}, {"word": " so", "start": 52.46, "end": 52.64, "probability": 0.9944621920585632}, {"word": " I", "start": 52.64, "end": 52.7, "probability": 0.9966464638710022}, {"word": " like", "start": 52.7, "end": 52.82, "probability": 0.9916961789131165}, {"word": " to", "start": 52.82, "end": 52.94, "probability": 0.9991183876991272}, {"word": " be", "start": 52.94, "end": 53.08, "probability": 0.9987573623657227}, {"word": " back", "start": 53.08, "end": 53.26, "probability": 0.9981616139411926}, {"word": " home", "start": 53.26, "end": 53.38, "probability": 0.996179461479187}, {"word": " by", "start": 53.38, "end": 53.62, "probability": 0.9976089000701904}, {"word": " 930", "start": 53.62, "end": 54.18, "probability": 0.6986310482025146}, {"word": " tops.", "start": 54.18, "end": 54.62, "probability": 0.6521551609039307}]}, {"id": 14, "seek": 5462, "start": 54.62, "end": 58.22, "text": " So many activities. I don't think I could keep up that pace,", "tokens": [50388, 407, 867, 5354, 13, 286, 500, 380, 519, 286, 727, 1066, 493, 300, 11638, 11, 50556], "temperature": 0.0, "avg_logprob": -0.08901551293163765, "compression_ratio": 1.4646464646464648, "no_speech_prob": 0.038449976593256, "words": [{"word": " So", "start": 54.62, "end": 55.38, "probability": 0.4011322557926178}, {"word": " many", "start": 55.38, "end": 55.72, "probability": 0.9835794568061829}, {"word": " activities.", "start": 55.72, "end": 56.24, "probability": 0.9940677881240845}, {"word": " I", "start": 56.56, "end": 56.68, "probability": 0.9947899580001831}, {"word": " don't", "start": 56.68, "end": 56.8, "probability": 0.9917812943458557}, {"word": " think", "start": 56.8, "end": 56.94, "probability": 0.9987900853157043}, {"word": " I", "start": 56.94, "end": 57.06, "probability": 0.9904001355171204}, {"word": " could", "start": 57.06, "end": 57.3, "probability": 0.8189982175827026}, {"word": " keep", "start": 57.3, "end": 57.52, "probability": 0.9980308413505554}, {"word": " up", "start": 57.52, "end": 57.7, "probability": 0.9978845715522766}, {"word": " that", "start": 57.7, "end": 57.92, "probability": 0.971761167049408}, {"word": " pace,", "start": 57.92, "end": 58.22, "probability": 0.9997972846031189}]}, {"id": 15, "seek": 5462, "start": 58.64, "end": 60.88, "text": " but it's nice to know you enjoy it to the fullest, Maria.", "tokens": [50556, 457, 309, 311, 1481, 281, 458, 291, 2103, 309, 281, 264, 45154, 11, 12734, 13, 50676], "temperature": 0.0, "avg_logprob": -0.08901551293163765, "compression_ratio": 1.4646464646464648, "no_speech_prob": 0.038449976593256, "words": [{"word": " but", "start": 58.64, "end": 58.78, "probability": 0.997028648853302}, {"word": " it's", "start": 58.78, "end": 58.98, "probability": 0.9932328164577484}, {"word": " nice", "start": 58.98, "end": 59.14, "probability": 0.998162567615509}, {"word": " to", "start": 59.14, "end": 59.34, "probability": 0.9978281855583191}, {"word": " know", "start": 59.34, "end": 59.46, "probability": 0.9991583824157715}, {"word": " you", "start": 59.46, "end": 59.7, "probability": 0.98508620262146}, {"word": " enjoy", "start": 59.7, "end": 59.94, "probability": 0.9836286306381226}, {"word": " it", "start": 59.94, "end": 60.14, "probability": 0.7867866158485413}, {"word": " to", "start": 60.14, "end": 60.18, "probability": 0.9943242073059082}, {"word": " the", "start": 60.18, "end": 60.3, "probability": 0.997702419757843}, {"word": " fullest,", "start": 60.3, "end": 60.54, "probability": 0.995789110660553}, {"word": " Maria.", "start": 60.54, "end": 60.88, "probability": 0.9910125136375427}]}, {"id": 16, "seek": 5462, "start": 61.54, "end": 64.44, "text": " I think I'll try to go out more often in the evening as well.", "tokens": [50704, 286, 519, 286, 603, 853, 281, 352, 484, 544, 2049, 294, 264, 5634, 382, 731, 13, 50836], "temperature": 0.0, "avg_logprob": -0.08901551293163765, "compression_ratio": 1.4646464646464648, "no_speech_prob": 0.038449976593256, "words": [{"word": " I", "start": 61.54, "end": 61.7, "probability": 0.9972327351570129}, {"word": " think", "start": 61.7, "end": 61.9, "probability": 0.9862807989120483}, {"word": " I'll", "start": 61.9, "end": 62.18, "probability": 0.9923642873764038}, {"word": " try", "start": 62.18, "end": 62.32, "probability": 0.9954238533973694}, {"word": " to", "start": 62.32, "end": 62.42, "probability": 0.9833545088768005}, {"word": " go", "start": 62.42, "end": 62.52, "probability": 0.997078537940979}, {"word": " out", "start": 62.52, "end": 62.64, "probability": 0.998121440410614}, {"word": " more", "start": 62.64, "end": 62.9, "probability": 0.9983955025672913}, {"word": " often", "start": 62.9, "end": 63.22, "probability": 0.9982287287712097}, {"word": " in", "start": 63.22, "end": 63.46, "probability": 0.9933239817619324}, {"word": " the", "start": 63.46, "end": 63.58, "probability": 0.9994378685951233}, {"word": " evening", "start": 63.58, "end": 63.78, "probability": 0.9951136708259583}, {"word": " as", "start": 63.78, "end": 64.04, "probability": 0.9317808747291565}, {"word": " well.", "start": 64.04, "end": 64.44, "probability": 0.9995704293251038}]}, {"id": 17, "seek": 5462, "start": 65.0, "end": 67.64, "text": " Sure, Brian. Just don't forget to give yourself time to rest.", "tokens": [50872, 4894, 11, 10765, 13, 1449, 500, 380, 2870, 281, 976, 1803, 565, 281, 1472, 13, 51024], "temperature": 0.0, "avg_logprob": -0.08901551293163765, "compression_ratio": 1.4646464646464648, "no_speech_prob": 0.038449976593256, "words": [{"word": " Sure,", "start": 65.0, "end": 65.18, "probability": 0.9777266383171082}, {"word": " Brian.", "start": 65.3, "end": 65.5, "probability": 0.9676694273948669}, {"word": " Just", "start": 65.78, "end": 65.94, "probability": 0.9862266182899475}, {"word": " don't", "start": 65.94, "end": 66.1, "probability": 0.9974634349346161}, {"word": " forget", "start": 66.1, "end": 66.28, "probability": 0.997865617275238}, {"word": " to", "start": 66.28, "end": 66.44, "probability": 0.9986770749092102}, {"word": " give", "start": 66.44, "end": 66.56, "probability": 0.9981229901313782}, {"word": " yourself", "start": 66.56, "end": 66.82, "probability": 0.998801589012146}, {"word": " time", "start": 66.82, "end": 67.08, "probability": 0.9975287318229675}, {"word": " to", "start": 67.08, "end": 67.32, "probability": 0.9991855025291443}, {"word": " rest.", "start": 67.32, "end": 67.64, "probability": 0.9994490742683411}]}, {"id": 18, "seek": 5462, "start": 67.96, "end": 69.84, "text": " Find what your interests are and have some fun.", "tokens": [51024, 11809, 437, 428, 8847, 366, 293, 362, 512, 1019, 13, 51140], "temperature": 0.0, "avg_logprob": -0.08901551293163765, "compression_ratio": 1.4646464646464648, "no_speech_prob": 0.038449976593256, "words": [{"word": " Find", "start": 67.96, "end": 68.2, "probability": 0.996134877204895}, {"word": " what", "start": 68.2, "end": 68.38, "probability": 0.9921560287475586}, {"word": " your", "start": 68.38, "end": 68.6, "probability": 0.9920014142990112}, {"word": " interests", "start": 68.6, "end": 68.78, "probability": 0.9987874627113342}, {"word": " are", "start": 68.78, "end": 69.12, "probability": 0.9985589385032654}, {"word": " and", "start": 69.12, "end": 69.28, "probability": 0.821259617805481}, {"word": " have", "start": 69.28, "end": 69.42, "probability": 0.9992271661758423}, {"word": " some", "start": 69.42, "end": 69.64, "probability": 0.9952657222747803}, {"word": " fun.", "start": 69.64, "end": 69.84, "probability": 0.9993378520011902}]}], "language": "en"}